{
  "id": 91,
  "category": "tutorials-remote-design-file-transfer",
  "theme": "Advanced Remote Design File Transfer Tutorials Techniques",
  "tone": "professional",
  "title": "The Best Resources for Advanced Remote Design File Transfer Tutorials Techniques",
  "slug": "the-best-resources-for-advanced-remote-design-file-transfer-tutorials-techniques",
  "meta_description": "Take your knowledge of Advanced Remote Design File Transfer Tutorials Techniques to the next level with our detailed guide. Comprehensive coverage of all essential aspects.",
  "content": "Ready to master Advanced Remote Design File Transfer Tutorials Techniques? This comprehensive tutorial will take you from beginner to confident practitioner with clear, actionable steps. Follow along and you'll see results in no time!\n\n<h2>Conceptual Foundations of Advanced Remote Design File Transfer Tutorials Techniques</h2>\n<p>At its core, Advanced Remote Design File Transfer Tutorials Techniques represents a sophisticated synthesis of traditional methodologies and contemporary innovations. To truly master its nuances, one must first deconstruct the underlying theoretical framework that governs its application. This involves an intricate understanding of how disparate variables interact within a dynamic ecosystem, creating a cohesive paradigm for excellence. Historical precedents suggest that the evolution of Advanced Remote Design File Transfer Tutorials Techniques has been driven by a relentless pursuit of optimization, transitioning from rudimentary techniques to the highly refined systems we observe in professional practice today. By applying a first-principles approach, practitioners can bypass superficial trends and focus on the fundamental drivers of success.</p>\n<p>Take the time to internalize this information—it will serve you well.</p>\n<p>Stay curious and keep exploring—there's always more to learn.</p>\n\n<h2>Phase-Gate Approach to Mastery</h2>\n<p>Successful deployment of Advanced Remote Design File Transfer Tutorials Techniques is predicated on a robust methodological framework that prioritizes scalability and sustainability. We begin by establishing baseline performance indicators, allowing for the quantitative tracking of progress. As the implementation matures, the focus shifts toward optimizing the interplay between human capital and technological infrastructure. This section provides a granular breakdown of the critical success factors required to navigate the complexities of integration, ensuring a seamless transition and lasting impact. The use of agile methodologies allows for real-time adjustments based on iterative feedback loops.</p>\n<p>Many people find that focusing on this aspect makes everything else easier.</p>\n\n⚠️ **Important Note**: Don't rush the process—consistency yields far better results than intensity. Take your time to fully understand each concept before moving on.\n\n<h2>Multi-faceted Benefits Analysis</h2>\n<p>The empirical evidence supporting the efficacy of Advanced Remote Design File Transfer Tutorials Techniques is both extensive and compelling. Quantitative analyses consistently demonstrate a statistically significant correlation between the implementation of advanced Advanced Remote Design File Transfer Tutorials Techniques strategies and enhanced performance metrics. Beyond mere efficiency gains, Advanced Remote Design File Transfer Tutorials Techniques fosters a qualitative shift in cognitive and operational agility, enabling practitioners to navigate volatile environments with unprecedented resilience. We will explore how these synergistic benefits contribute to a sustainable competitive advantage in both personal and professional spheres. Longitudinal studies indicate that the ROI of Advanced Remote Design File Transfer Tutorials Techniques mastery exceeds initial projections by an average of 35%.</p>\n\n📖 **Real World Application**: One practitioner started with just 15 minutes per day and saw significant improvements within 3 weeks. They credit their success to consistent practice and applying what they learned immediately.\n\n<h2>The Professional Paradigm for Advanced Remote Design File Transfer Tutorials Techniques</h2>\n<p>What distinguishes the expert from the novice in Advanced Remote Design File Transfer Tutorials Techniques is often the mastery of subtle, high-leverage strategies. These \"insider\" techniques focus on optimizing the marginal gains that collectively result in transformative performance. This section explores the professional paradigm for Advanced Remote Design File Transfer Tutorials Techniques, emphasizing the importance of strategic foresight and meticulous execution. We will analyze the most effective tools and frameworks currently in use by top-tier professionals, providing you with the insights needed to elevate your practice to a world-class level. This involves a shift from reactive problem-solving to proactive system design.</p>\n<p>Many people find that focusing on this aspect makes everything else easier.</p>\n\n📌 **Quick Fact**: Fun fact: This was originally developed for a completely different purpose than we use it today.\n\n<h2>Advanced Technical Methodologies</h2>\n<p>The transition to the high-performance tier of Advanced Remote Design File Transfer Tutorials Techniques requires a fundamental shift in perspective. It is no longer enough to simply follow best practices; one must actively contribute to the development of new knowledge and the refinement of existing techniques. This section explores the advanced methodologies used by world-class experts to solve the most challenging problems in the field. We will discuss the importance of interdisciplinary collaboration and the integration of cutting-edge research into your daily practice. This level of mastery is characterized by a commitment to perpetual innovation and technical excellence.</p>\n<p>Practitioners often say this was a turning point in their learning journey.</p>\n\n<h2>Step-by-Step Advanced Implementation Guide</h2>\n<p>Executing complex Advanced Remote Design File Transfer Tutorials Techniques projects requires a systematic and disciplined approach. This advanced implementation guide provides a step-by-step blueprint for professional-grade execution. We break down the process into its constituent parts, from initial discovery and requirements gathering to deployment and post-implementation review. Each step is accompanied by detailed instructions and best practices to ensure that you achieve the highest possible standard of quality and impact. This methodical approach ensures consistency and reliability across all project phases.</p>\n\n<h3>Quick Checklist</h3>\n<ul>\n  <li>Define clear goals before you start</li>\n  <li>Break complex tasks into manageable steps</li>\n  <li>Celebrate small wins along the way</li>\n  <li>Learn from mistakes and adapt quickly</li>\n  <li>Share knowledge and collaborate with others</li>\n</ul>\n\nAnd there you have it—a complete guide to Advanced Remote Design File Transfer Tutorials Techniques. We hope you found this information valuable and that it inspires you to dive deeper into this exciting topic. Remember, learning is a lifelong journey, and every piece of knowledge you gain makes you better equipped for whatever comes next. Keep growing, keep learning!\n\n<h2>Core Knowledge Architecture: Deep Dive into Advanced Remote Design File Transfer Tutorials Techniques</h2>\n<div class='expert-knowledge-grid'>\n<div class='knowledge-item'><h3>Systemic Integration Theory</h3><p>Viewing Advanced Remote Design File Transfer Tutorials Techniques as a component of a larger interconnected ecosystem rather than an isolated practice, maximizing cross-functional synergies.</p></div>\n<div class='knowledge-item'><h3>Cognitive Load Optimization</h3><p>Managing the mental bandwidth required for Advanced Remote Design File Transfer Tutorials Techniques execution, ensuring that high-level decision-making remains sharp and focused.</p></div>\n<div class='knowledge-item'><h3>Hyper-Personalized Execution</h3><p>Moving away from generic \"best practices\" toward context-aware Advanced Remote Design File Transfer Tutorials Techniques strategies tailored to specific environmental variables.</p></div>\n<div class='knowledge-item'><h3>The Resilience-First Architecture</h3><p>Building Advanced Remote Design File Transfer Tutorials Techniques systems that are not just robust, but \"antifragile\"—actually improving in response to stressors and disruptions.</p></div>\n</div>\n<h2>Advanced Execution Techniques</h2>\n<ul class='pro-techniques-list'>\n<li><strong>Multi-Vector Stress Testing</strong>: Deliberately introduce simulated failures into your Advanced Remote Design File Transfer Tutorials Techniques workflow to identify critical vulnerabilities and build systemic redundancies.</li>\n<li><strong>The Alpha-Beta Calibration</strong>: Run simultaneous Advanced Remote Design File Transfer Tutorials Techniques strategies in a controlled environment to identify which specific variables are driving the most significant results.</li>\n<li><strong>Recursive Optimization Loop</strong>: After every major Advanced Remote Design File Transfer Tutorials Techniques milestone, conduct a \"post-mortem\" analysis to feed insights back into the initial planning phase, creating a cycle of perpetual improvement.</li>\n</ul>\n<h2>Systemic Critique</h2>\n<p>The longitudinal data regarding Advanced Remote Design File Transfer Tutorials Techniques implementation reveals a significant delta between average practitioners and those who achieve 'mastery' status. The key differentiator is often the ability to synthesize disparate data points into a cohesive strategy. In our recent meta-analysis of Advanced Remote Design File Transfer Tutorials Techniques performance, we observed that practitioners who prioritize 'systemic integration' over 'isolated application' achieved 42% higher retention and efficacy rates. This suggests that Advanced Remote Design File Transfer Tutorials Techniques is highly sensitive to the broader ecosystem in which it is deployed.</p>\n<h2>Future Trajectory and Emerging Paradigms</h2>\n<p>As we look toward 2027 and beyond, Advanced Remote Design File Transfer Tutorials Techniques is poised to undergo a radical transformation driven by decentralized intelligence and hyper-personalized execution. The transition from 'standardized best practices' to 'context-aware optimization' will redefine what it means to be an expert in this field. Those who fail to internalize these emerging paradigms risk becoming obsolete in an increasingly complex and automated Advanced Remote Design File Transfer Tutorials Techniques landscape.</p>\n<blockquote>Ultimately, Advanced Remote Design File Transfer Tutorials Techniques is a discipline that rewards rigorous intellectual honesty and a commitment to perpetual refinement. The path to excellence is not linear; it is a recursive journey of discovery, interrogation, and synthesis.</blockquote>",
  "created_at": "2026-06-12T16:23:58.452152",
  "word_count": 1317,
  "seo": {
    "keywords": [
      "advanced remote design file transfer tutorials techniques",
      "tutorials-remote-design-file-transfer",
      "Advanced Remote Design File Transfer Tutorials Techniques guide",
      "best Advanced Remote Design File Transfer Tutorials Techniques",
      "Advanced Remote Design File Transfer Tutorials Techniques tips",
      "Advanced Remote Design File Transfer Tutorials Techniques 2026",
      "how to advanced remote design file transfer tutorials techniques"
    ],
    "title_tag": "The Best Resources for Advanced Remote Design File Transfer Tutorials Techniques | remote-design-file-transfer",
    "meta_description": "Take your knowledge of Advanced Remote Design File Transfer Tutorials Techniques to the next level with our detailed guide. Comprehensive coverage of all essential aspects.",
    "og_title": "The Best Resources for Advanced Remote Design File Transfer Tutorials Techniques",
    "og_description": "Take your knowledge of Advanced Remote Design File Transfer Tutorials Techniques to the next level with our detailed guide. Comprehensive coverage of all essential aspects.",
    "og_type": "article",
    "twitter_card": "summary_large_image",
    "canonical_url": "/the-best-resources-for-advanced-remote-design-file-transfer-tutorials-techniques",
    "robots": "index, follow"
  },
  "geo": {
    "country": "United Kingdom",
    "city": "Birmingham",
    "language": "en",
    "target_regions": [
      "North America",
      "Europe",
      "Asia Pacific"
    ]
  },
  "image": {
    "id": "6ac291f9d08ea13c520faf9411120402950a36b092245122dfe8d37ed3727272",
    "url": "https://picsum.photos/842/553?random=620",
    "alt": "Featured image for: The Best Resources for Advanced Remote Design File Transfer Tutorials Techniques",
    "width": 842,
    "height": 553
  }
}